wdm/__init__.py
wdm/__main__.py
wdm/check.py
wdm/cli.py
wdm/exceptions.py
wdm/version.py
wdm/wdm.json
wdm/wdm.py
wdm-0.3.2.dist-info/AUTHORS.rst
wdm-0.3.2.dist-info/LICENSE
wdm-0.3.2.dist-info/METADATA
wdm-0.3.2.dist-info/WHEEL
wdm-0.3.2.dist-info/entry_points.txt
wdm-0.3.2.dist-info/top_level.txt
wdm-0.3.2.dist-info/RECORD
