Metadata-Version: 2.1
Name: wdm
Version: 0.3.2
Summary: webOS device manager
Home-page: https://github.com/webosose-emulator/wdm
Author: Heegoo Han
Author-email: hghan9@gmail.com
License: MIT license
Keywords: wdm
Classifier: Development Status :: 2 - Pre-Alpha
Classifier: Intended Audience :: Developers
Classifier: License :: OSI Approved :: MIT License
Classifier: Natural Language :: English
Classifier: Programming Language :: Python :: 3
Classifier: Programming Language :: Python :: 3.6
Classifier: Programming Language :: Python :: 3.7
Classifier: Programming Language :: Python :: 3.8
Requires-Python: >=3.6
License-File: LICENSE
License-File: AUTHORS.rst
